README.md
geva.py
setup.py
Geva.egg-info/PKG-INFO
Geva.egg-info/SOURCES.txt
Geva.egg-info/dependency_links.txt
Geva.egg-info/requires.txt
Geva.egg-info/top_level.txt