Metadata-Version: 2.1
Name: Geva
Version: 1.0.1
Summary: A genomic assement tools including Completeness and Accuracy
Home-page: https://github.com/panlab-bioinfo/Geva.git
Author: yangjinbao
Author-email: ruoyu1123@outlook.com
Classifier: Development Status :: 5 - Production/Stable
Classifier: Intended Audience :: Science/Research
Classifier: License :: OSI Approved :: MIT License
Classifier: Programming Language :: Python :: 3
Classifier: Programming Language :: Python :: 3.7
Classifier: Programming Language :: Python :: 3.8
Classifier: Programming Language :: Python :: 3.9
Requires-Python: >=3.7
